
{
    "systems": [
        { "name": "Sol", "folder": "systems/sol" }
    ],

    "ships": [
        {
            "name": "SG:Space Glider",
            "tag": "SG-01",
            "module": "glider",
            "status": "landed",
            "target": "Sol/Earth",
            "location": [ 28.632307, -80.705774 ],
            "heading": 150
        },
        {
            "name": "SG:Space Glider",
            "tag": "SG-02",
            "module": "glider",
            "status": "landed",
            "target": "Sol/Earth",
            "location": [ 28.632307, -80.705774 ],
            "heading": 150
        }
    ],

    "player": {
        "mode": {
            "type": "target-sync",
            "target": "Sol/Earth", "sync-target": "Sol",
            "direction": [0, 0, 1], "scale": 4
        },
        "travel": "free",
        "fov": 50.0
    }
}